conduitpkg/__about__.py
conduitpkg/__init__.py
conduitpkg/cpkg_cli.py
conduitpkg/postinstall.py
conduitpkg/api/__init__.py
conduitpkg/api/advanced.py
conduitpkg/builder/__init__.py
conduitpkg/builder/new_packet.py
conduitpkg/cli/__init__.py
conduitpkg/cli/parsertoapi.py
conduitpkg/gui/__init__.py
conduitpkg/install/__init__.py
conduitpkg/install/dependencies.py
conduitpkg/install/entries.py
conduitpkg/install/install_pkg.py
conduitpkg/install/search_packet.py
conduitpkg/packaging/__init__.py
conduitpkg/packaging/compress/__init__.py
conduitpkg/packaging/compress/compress_packet.py
conduitpkg/packaging/extracting/__init__.py
conduitpkg/packaging/extracting/extract_packet.py
conduitpkg/templates/__init__.py
conduitpkg/templates/builder_template.py
conduitpkg/templates/gpl_template.py
conduitpkg/templates/package_template.py
conduitpkg-1.0.0.dist-info/METADATA
conduitpkg-1.0.0.dist-info/WHEEL
conduitpkg-1.0.0.dist-info/entry_points.txt
conduitpkg-1.0.0.dist-info/licenses/LICENSE.txt
conduitpkg-1.0.0.dist-info/RECORD
