Metadata-Version: 2.4
Name: conduitpkg
Version: 1.0.0
Summary: A simple packet manager, works with github to upload packets.
Project-URL: Documentation, https://github.com/guille-ux/conduitpkg#readme
Project-URL: Issues, https://github.com/guille-ux/conduitpkg/issues
Project-URL: Source, https://github.com/guille-ux/conduitpkg
Author-email: Guille on a Raspberry pi <guilleleiratemes@gmail.com>
License-Expression: GPL-3.0-or-later
License-File: LICENSE.txt
Classifier: Development Status :: 4 - Beta
Classifier: Programming Language :: Python
Classifier: Programming Language :: Python :: 3.8
Classifier: Programming Language :: Python :: 3.9
Classifier: Programming Language :: Python :: 3.10
Classifier: Programming Language :: Python :: 3.11
Classifier: Programming Language :: Python :: 3.12
Classifier: Programming Language :: Python :: Implementation :: CPython
Classifier: Programming Language :: Python :: Implementation :: PyPy
Requires-Python: >=3.7
Requires-Dist: zynk-lite>=0.3.2
